calibrator/__init__.py
calibrator/calibrator.py
calibrator/local_calibrator.py
calibrator/temperature_scaling.py
calibrator/metrics/__init__.py
calibrator/metrics/accuracy.py
calibrator/metrics/adaptiveece.py
calibrator/metrics/classwiseece.py
calibrator/metrics/ece.py
calibrator/metrics/nll.py
calibrator-0.0.12.dist-info/LICENSE
calibrator-0.0.12.dist-info/METADATA
calibrator-0.0.12.dist-info/WHEEL
calibrator-0.0.12.dist-info/top_level.txt
calibrator-0.0.12.dist-info/RECORD
